sinkhorn_knopp/__init__.py
sinkhorn_knopp/sinkhorn_knopp.py
sinkhorn_knopp-0.2.dist-info/DESCRIPTION.rst
sinkhorn_knopp-0.2.dist-info/METADATA
sinkhorn_knopp-0.2.dist-info/RECORD
sinkhorn_knopp-0.2.dist-info/WHEEL
sinkhorn_knopp-0.2.dist-info/metadata.json
sinkhorn_knopp-0.2.dist-info/top_level.txt
