Metadata-Version: 2.0
Name: sinkhorn-knopp
Version: 0.2
Summary: Sinkhorn-Knopp Algorithm
Home-page: https://github.com/btaba/sinkhorn_knopp
Author: Baruch Tabanpour
Author-email: baruch@tabanpour.info
License: MIT
Keywords: sinkhorn-knopp,doubly stochastic matrix
Platform: UNKNOWN
Classifier: Development Status :: 2 - Pre-Alpha
Classifier: Intended Audience :: Science/Research
Classifier: License :: OSI Approved :: MIT License
Classifier: Topic :: Scientific/Engineering :: Information Analysis
Classifier: Programming Language :: Python :: 2.7
Classifier: Programming Language :: Python :: 3.5
Classifier: Programming Language :: Python :: 3.6
Requires-Dist: numpy (>=1)
